COPYING.txt
MANIFEST.in
README.txt
setup.py
mixrestview/__init__.py
mixrestview/apiform.py
mixrestview/apirender.py
mixrestview/apiview.py
mixrestview/fields.py
mixrestview/mixview.py
mixrestview/param.py
mixrestview/sites.py
mixrestview/utils.py
mixrestview/validators.py
mixrestview/widgets.py
mixrestview.egg-info/PKG-INFO
mixrestview.egg-info/SOURCES.txt
mixrestview.egg-info/dependency_links.txt
mixrestview.egg-info/top_level.txt
mixrestview.egg-info/zip-safe
mixrestview/static/mixrestview/highlight/js/highlight.pack.js
mixrestview/static/mixrestview/js/popover.js
mixrestview/static/mixrestview/js/tooltip.js
mixrestview/templates/webapi.html