Metadata-Version: 1.1
Name: mixrestview
Version: 1.0.11
Summary: validate request params.
Home-page: https://github.com/TNT1314/mixrestview.git
Author: wormer
Author-email: wormer@wormer.cn
License: MIT
Keywords: python django rest-framework params validator
Platform: UNKNOWN
Classifier: License :: OSI Approved :: MIT License
Classifier: Programming Language :: Python
Classifier: Intended Audience :: Developers
Classifier: Operating System :: OS Independent
Requires: django
Requires: djangorestframework
